liquidai/__init__.py
liquidai/client.py
liquidai-1.0.1.dist-info/LICENSE
liquidai-1.0.1.dist-info/METADATA
liquidai-1.0.1.dist-info/WHEEL
liquidai-1.0.1.dist-info/top_level.txt
liquidai-1.0.1.dist-info/RECORD
