Metadata-Version: 2.1
Name: liquidai
Version: 1.0.1
Summary: Client library for the Liquid AI API
Author-email: Mathias Lechner <mathias@liquid.ai>, Kelvin He <kelvin@liquid.ai>
License: Apache License
Project-URL: Homepage, https://liquid.ai
Project-URL: Documentation, https://readthedocs.org
Project-URL: Repository, https://github.com/Liquid4All/liquid_client
Keywords: liquidai,api
Classifier: Development Status :: 4 - Beta
Classifier: Programming Language :: Python
Requires-Python: >=3.6
License-File: LICENSE
Requires-Dist: httpx
